{"nodes": [{"id": "edge_audit_audit_py", "label": "audit.py", "file_type": "code", "source_file": "edge/audit/audit.py", "source_location": "L1"}, {"id": "audit_auditlogger", "label": "AuditLogger", "file_type": "code", "source_file": "edge/audit/audit.py", "source_location": "L18"}, {"id": "audit_auditlogger_init", "label": ".__init__()", "file_type": "code", "source_file": "edge/audit/audit.py", "source_location": "L21"}, {"id": "audit_auditlogger_log", "label": ".log()", "file_type": "code", "source_file": "edge/audit/audit.py", "source_location": "L32"}, {"id": "audit_auditlogger_log_ssh_command", "label": ".log_ssh_command()", "file_type": "code", "source_file": "edge/audit/audit.py", "source_location": "L70"}, {"id": "audit_auditlogger_log_ssh_connection", "label": ".log_ssh_connection()", "file_type": "code", "source_file": "edge/audit/audit.py", "source_location": "L90"}, {"id": "audit_auditlogger_get_recent_logs", "label": ".get_recent_logs()", "file_type": "code", "source_file": "edge/audit/audit.py", "source_location": "L108"}, {"id": "audit_auditlogger_search_logs", "label": ".search_logs()", "file_type": "code", "source_file": "edge/audit/audit.py", "source_location": "L134"}, {"id": "audit_rationale_1", "label": "\u5ba1\u8ba1\u65e5\u5fd7\u8bb0\u5f55\u5668  \u8bb0\u5f55SSH\u6267\u884c\u5668\u7684\u64cd\u4f5c\u65e5\u5fd7", "file_type": "rationale", "source_file": "edge/audit/audit.py", "source_location": "L1"}], "edges": [{"source": "edge_audit_audit_py", "target": "json", "relation": "imports", "confidence": "EXTRACTED", "source_file": "edge/audit/audit.py", "source_location": "L7", "weight": 1.0}, {"source": "edge_audit_audit_py", "target": "logging", "relation": "imports", "confidence": "EXTRACTED", "source_file": "edge/audit/audit.py", "source_location": "L8", "weight": 1.0}, {"source": "edge_audit_audit_py", "target": "datetime", "relation": "imports_from", "confidence": "EXTRACTED", "source_file": "edge/audit/audit.py", "source_location": "L9", "weight": 1.0}, {"source": "edge_audit_audit_py", "target": "pathlib", "relation": "imports_from", "confidence": "EXTRACTED", "source_file": "edge/audit/audit.py", "source_location": "L10", "weight": 1.0}, {"source": "edge_audit_audit_py", "target": "typing", "relation": "imports_from", "confidence": "EXTRACTED", "source_file": "edge/audit/audit.py", "source_location": "L11", "weight": 1.0}, {"source": "edge_audit_audit_py", "target": "threading", "relation": "imports_from", "confidence": "EXTRACTED", "source_file": "edge/audit/audit.py", "source_location": "L12", "weight": 1.0}, {"source": "edge_audit_audit_py", "target": "audit_auditlogger", "relation": "contains", "confidence": "EXTRACTED", "source_file": "edge/audit/audit.py", "source_location": "L18", "weight": 1.0}, {"source": "audit_auditlogger", "target": "audit_auditlogger_init", "relation": "method", "confidence": "EXTRACTED", "source_file": "edge/audit/audit.py", "source_location": "L21", "weight": 1.0}, {"source": "audit_auditlogger", "target": "audit_auditlogger_log", "relation": "method", "confidence": "EXTRACTED", "source_file": "edge/audit/audit.py", "source_location": "L32", "weight": 1.0}, {"source": "audit_auditlogger", "target": "audit_auditlogger_log_ssh_command", "relation": "method", "confidence": "EXTRACTED", "source_file": "edge/audit/audit.py", "source_location": "L70", "weight": 1.0}, {"source": "audit_auditlogger", "target": "audit_auditlogger_log_ssh_connection", "relation": "method", "confidence": "EXTRACTED", "source_file": "edge/audit/audit.py", "source_location": "L90", "weight": 1.0}, {"source": "audit_auditlogger", "target": "audit_auditlogger_get_recent_logs", "relation": "method", "confidence": "EXTRACTED", "source_file": "edge/audit/audit.py", "source_location": "L108", "weight": 1.0}, {"source": "audit_auditlogger", "target": "audit_auditlogger_search_logs", "relation": "method", "confidence": "EXTRACTED", "source_file": "edge/audit/audit.py", "source_location": "L134", "weight": 1.0}, {"source": "audit_auditlogger_log_ssh_command", "target": "audit_auditlogger_log", "relation": "calls", "confidence": "EXTRACTED", "source_file": "edge/audit/audit.py", "source_location": "L74", "weight": 1.0}, {"source": "audit_auditlogger_log_ssh_connection", "target": "audit_auditlogger_log", "relation": "calls", "confidence": "EXTRACTED", "source_file": "edge/audit/audit.py", "source_location": "L98", "weight": 1.0}, {"source": "audit_rationale_1", "target": "edge_audit_audit_py", "relation": "rationale_for", "confidence": "EXTRACTED", "source_file": "edge/audit/audit.py", "source_location": "L1", "weight": 1.0}]}