{"nodes": [{"id": "tests_run_all_tests_py", "label": "run_all_tests.py", "file_type": "code", "source_file": "tests/run_all_tests.py", "source_location": "L1"}, {"id": "run_all_tests_run_command", "label": "run_command()", "file_type": "code", "source_file": "tests/run_all_tests.py", "source_location": "L12"}, {"id": "run_all_tests_main", "label": "main()", "file_type": "code", "source_file": "tests/run_all_tests.py", "source_location": "L50"}, {"id": "run_all_tests_rationale_1", "label": "\u6d4b\u8bd5\u8fd0\u884c\u5668 - \u8fd0\u884c\u6240\u6709\u6d4b\u8bd5\u5957\u4ef6  \u6267\u884c\u5355\u5143\u6d4b\u8bd5\u3001\u96c6\u6210\u6d4b\u8bd5\u548c\u7aef\u5230\u7aef\u6d4b\u8bd5", "file_type": "rationale", "source_file": "tests/run_all_tests.py", "source_location": "L1"}], "edges": [{"source": "tests_run_all_tests_py", "target": "subprocess", "relation": "imports", "confidence": "EXTRACTED", "source_file": "tests/run_all_tests.py", "source_location": "L7", "weight": 1.0}, {"source": "tests_run_all_tests_py", "target": "sys", "relation": "imports", "confidence": "EXTRACTED", "source_file": "tests/run_all_tests.py", "source_location": "L8", "weight": 1.0}, {"source": "tests_run_all_tests_py", "target": "time", "relation": "imports", "confidence": "EXTRACTED", "source_file": "tests/run_all_tests.py", "source_location": "L9", "weight": 1.0}, {"source": "tests_run_all_tests_py", "target": "run_all_tests_run_command", "relation": "contains", "confidence": "EXTRACTED", "source_file": "tests/run_all_tests.py", "source_location": "L12", "weight": 1.0}, {"source": "tests_run_all_tests_py", "target": "run_all_tests_main", "relation": "contains", "confidence": "EXTRACTED", "source_file": "tests/run_all_tests.py", "source_location": "L50", "weight": 1.0}, {"source": "run_all_tests_main", "target": "run_all_tests_run_command", "relation": "calls", "confidence": "EXTRACTED", "source_file": "tests/run_all_tests.py", "source_location": "L59", "weight": 1.0}, {"source": "run_all_tests_rationale_1", "target": "tests_run_all_tests_py", "relation": "rationale_for", "confidence": "EXTRACTED", "source_file": "tests/run_all_tests.py", "source_location": "L1", "weight": 1.0}]}