{"nodes": [{"id": "cloud_init_py", "label": "__init__.py", "file_type": "code", "source_file": "cloud/__init__.py", "source_location": "L1"}, {"id": "init_rationale_1", "label": "HermesNexus \u4e91\u7aef\u670d\u52a1  \u63d0\u4f9b\u4e91\u7aef\u63a7\u5236\u5e73\u9762\u7684\u6838\u5fc3\u529f\u80fd", "file_type": "rationale", "source_file": "cloud/__init__.py", "source_location": "L1"}], "edges": [{"source": "init_rationale_1", "target": "cloud_init_py", "relation": "rationale_for", "confidence": "EXTRACTED", "source_file": "cloud/__init__.py", "source_location": "L1", "weight": 1.0}]}